{
    "category": "Housing and Buildings",
    "endpoint": "dx7g-zwbx",
    "url": "https://data.sfgov.org/Housing-and-Buildings/Reference-Assessor-Recorder-Neighborhood-Codes/dx7g-zwbx",
    "title": "Reference: Assessor-Recorder Neighborhood Codes",
    "description": "Neighborhood code reference dataset for the <a href=\"https://data.sfgov.org/d/wv5m-vpq2\">Assessor Historical Secured Property Tax Rolls</a> dataset",
    "columns": [
        {
            "name": "District",
            "fieldName": "district",
            "dataTypeName": "number",
            "description": "The neighborhood district number. Districts group together a subset of neighborhoods.",
            "position": 1,
            "renderTypeName": "number",
            "tableColumnId": 580353698
        },
        {
            "name": "Code",
            "fieldName": "code",
            "dataTypeName": "text",
            "description": "The neighborhood code",
            "position": 2,
            "renderTypeName": "text",
            "tableColumnId": 580353699
        },
        {
            "name": "Neighborhood",
            "fieldName": "neighborhood",
            "dataTypeName": "text",
            "description": "The neighborhood name corresponding to the field \"Code\"",
            "position": 3,
            "renderTypeName": "text",
            "tableColumnId": 580353700
        }
    ],
    "publishing_department": "Assessor-Recorder",
    "rows_updated_at": "2023-08-31T16:43:59Z"
}