{
    "category": "Housing and Buildings",
    "endpoint": "893e-xam6",
    "url": "https://data.sfgov.org/Housing-and-Buildings/Fire-Permits/893e-xam6",
    "title": "Fire Permits",
    "description": "Information on Fire Permits issued by the Fire Department for a particular location. Key fields include Permit Number, Permit Type, Address, Permit Start Dt, Permit Status, Special Conditions, Location.",
    "columns": [
        {
            "name": "Permit Number",
            "fieldName": "permit_number",
            "dataTypeName": "text",
            "description": null,
            "position": 1,
            "renderTypeName": "text",
            "tableColumnId": 591225199
        },
        {
            "name": "Permit Type",
            "fieldName": "permit_type",
            "dataTypeName": "text",
            "description": null,
            "position": 2,
            "renderTypeName": "text",
            "tableColumnId": 591225200
        },
        {
            "name": "Permit Type Description",
            "fieldName": "permit_type_description",
            "dataTypeName": "text",
            "description": null,
            "position": 3,
            "renderTypeName": "text",
            "tableColumnId": 591225201
        },
        {
            "name": "Permit Address",
            "fieldName": "permit_address",
            "dataTypeName": "text",
            "description": null,
            "position": 4,
            "renderTypeName": "text",
            "tableColumnId": 591225202
        },
        {
            "name": "Permit Zipcode",
            "fieldName": "permit_zipcode",
            "dataTypeName": "text",
            "description": null,
            "position": 5,
            "renderTypeName": "text",
            "tableColumnId": 591225203
        },
        {
            "name": "Battalion",
            "fieldName": "battalion",
            "dataTypeName": "text",
            "description": null,
            "position": 6,
            "renderTypeName": "text",
            "tableColumnId": 591225204
        },
        {
            "name": "Station Area",
            "fieldName": "station_area",
            "dataTypeName": "text",
            "description": null,
            "position": 7,
            "renderTypeName": "text",
            "tableColumnId": 591225205
        },
        {
            "name": "Fire Prevention District",
            "fieldName": "bureau_of_fire_prevention_district",
            "dataTypeName": "text",
            "description": null,
            "position": 8,
            "renderTypeName": "text",
            "tableColumnId": 591225206
        },
        {
            "name": "Permit Application Date",
            "fieldName": "permit_application_date",
            "dataTypeName": "calendar_date",
            "description": "",
            "position": 9,
            "renderTypeName": "calendar_date",
            "tableColumnId": 591225207
        },
        {
            "name": "Permit Date Approved",
            "fieldName": "permit_date_approved",
            "dataTypeName": "calendar_date",
            "description": "Permit Date Approved",
            "position": 10,
            "renderTypeName": "calendar_date",
            "tableColumnId": 591225208
        },
        {
            "name": "Inspection Number",
            "fieldName": "inspection_number",
            "dataTypeName": "number",
            "description": null,
            "position": 11,
            "renderTypeName": "number",
            "tableColumnId": 591225209
        },
        {
            "name": "Expiration Date",
            "fieldName": "expiration_date",
            "dataTypeName": "calendar_date",
            "description": "",
            "position": 12,
            "renderTypeName": "calendar_date",
            "tableColumnId": 591225210
        },
        {
            "name": "Night Place of Assembly Permit",
            "fieldName": "night_place_of_assembly_permit",
            "dataTypeName": "checkbox",
            "description": null,
            "position": 13,
            "renderTypeName": "checkbox",
            "tableColumnId": 591225211
        },
        {
            "name": "Permit Status",
            "fieldName": "permit_status",
            "dataTypeName": "text",
            "description": null,
            "position": 14,
            "renderTypeName": "text",
            "tableColumnId": 591225212
        },
        {
            "name": "Inspection Date",
            "fieldName": "inspection_date",
            "dataTypeName": "calendar_date",
            "description": "",
            "position": 15,
            "renderTypeName": "calendar_date",
            "tableColumnId": 591225213
        },
        {
            "name": "Hearing Calendar Date",
            "fieldName": "hearing_calendar_date",
            "dataTypeName": "calendar_date",
            "description": "",
            "position": 16,
            "renderTypeName": "calendar_date",
            "tableColumnId": 591225214
        },
        {
            "name": "Hearing Status",
            "fieldName": "hearing_status",
            "dataTypeName": "text",
            "description": null,
            "position": 17,
            "renderTypeName": "text",
            "tableColumnId": 591225215
        },
        {
            "name": "Permit Fee",
            "fieldName": "permit_fee",
            "dataTypeName": "number",
            "description": null,
            "position": 18,
            "renderTypeName": "number",
            "tableColumnId": 591225216
        },
        {
            "name": "Referral Fee",
            "fieldName": "referral_fee",
            "dataTypeName": "number",
            "description": null,
            "position": 19,
            "renderTypeName": "number",
            "tableColumnId": 591225217
        },
        {
            "name": "Posting Fee",
            "fieldName": "posting_fee",
            "dataTypeName": "number",
            "description": null,
            "position": 20,
            "renderTypeName": "number",
            "tableColumnId": 591225218
        },
        {
            "name": "Date all permit fees were paid",
            "fieldName": "date_all_permit_fees_were_paid",
            "dataTypeName": "calendar_date",
            "description": "",
            "position": 21,
            "renderTypeName": "calendar_date",
            "tableColumnId": 591225219
        },
        {
            "name": "Unit Count",
            "fieldName": "unit_count",
            "dataTypeName": "text",
            "description": null,
            "position": 22,
            "renderTypeName": "text",
            "tableColumnId": 591225220
        },
        {
            "name": "Unit Type",
            "fieldName": "unit_type",
            "dataTypeName": "text",
            "description": null,
            "position": 23,
            "renderTypeName": "text",
            "tableColumnId": 591225221
        },
        {
            "name": "Permit Holder",
            "fieldName": "permit_holder",
            "dataTypeName": "text",
            "description": null,
            "position": 24,
            "renderTypeName": "text",
            "tableColumnId": 591225222
        },
        {
            "name": "Tax Class",
            "fieldName": "tax_class",
            "dataTypeName": "text",
            "description": null,
            "position": 25,
            "renderTypeName": "text",
            "tableColumnId": 591225223
        },
        {
            "name": "DBA Name associated with this permit holder",
            "fieldName": "dba_name_associated_with_this_permit_holder",
            "dataTypeName": "text",
            "description": null,
            "position": 26,
            "renderTypeName": "text",
            "tableColumnId": 591225224
        },
        {
            "name": "Supervisor District",
            "fieldName": "supervisor_district",
            "dataTypeName": "text",
            "description": null,
            "position": 27,
            "renderTypeName": "text",
            "tableColumnId": 591225225
        },
        {
            "name": "Neighborhood  District",
            "fieldName": "neighborhood_district",
            "dataTypeName": "text",
            "description": null,
            "position": 28,
            "renderTypeName": "text",
            "tableColumnId": 591225226
        },
        {
            "name": "location",
            "fieldName": "location",
            "dataTypeName": "point",
            "description": "",
            "position": 29,
            "renderTypeName": "point",
            "tableColumnId": 591225227
        },
        {
            "name": "data_as_of",
            "fieldName": "data_as_of",
            "dataTypeName": "calendar_date",
            "description": "Timestamp the data was updated in the source system",
            "position": 30,
            "renderTypeName": "calendar_date",
            "tableColumnId": 591225233
        },
        {
            "name": "data_loaded_at",
            "fieldName": "data_loaded_at",
            "dataTypeName": "calendar_date",
            "description": "Timestamp the data was loaded to the open data portal",
            "position": 31,
            "renderTypeName": "calendar_date",
            "tableColumnId": 591225234
        },
        {
            "name": "Current Police Districts",
            "fieldName": ":@computed_region_qgnn_b9vv",
            "dataTypeName": "number",
            "description": "This column was automatically created in order to record in what polygon from the dataset 'Current Police Districts' (qgnn-b9vv) the point in column 'location' is located.  This enables the creation of region maps (choropleths) in the visualization canvas and data lens.",
            "position": 32,
            "renderTypeName": "number",
            "tableColumnId": 591225230
        },
        {
            "name": "Current Supervisor Districts",
            "fieldName": ":@computed_region_26cr_cadq",
            "dataTypeName": "number",
            "description": "This column was automatically created in order to record in what polygon from the dataset 'Current Supervisor Districts' (26cr-cadq) the point in column 'location' is located.  This enables the creation of region maps (choropleths) in the visualization canvas and data lens.",
            "position": 33,
            "renderTypeName": "number",
            "tableColumnId": 591225231
        },
        {
            "name": "Analysis Neighborhoods",
            "fieldName": ":@computed_region_ajp5_b2md",
            "dataTypeName": "number",
            "description": "This column was automatically created in order to record in what polygon from the dataset 'Analysis Neighborhoods' (ajp5-b2md) the point in column 'location' is located.  This enables the creation of region maps (choropleths) in the visualization canvas and data lens.",
            "position": 34,
            "renderTypeName": "number",
            "tableColumnId": 591225232
        },
        {
            "name": "Neighborhoods",
            "fieldName": ":@computed_region_jwn9_ihcz",
            "dataTypeName": "number",
            "description": "This column was automatically created in order to record in what polygon from the dataset 'Neighborhoods' (jwn9-ihcz) the point in column 'location' is located.  This enables the creation of region maps (choropleths) in the visualization canvas and data lens.",
            "position": 35,
            "renderTypeName": "number",
            "tableColumnId": 591225228
        },
        {
            "name": "SF Find Neighborhoods",
            "fieldName": ":@computed_region_6qbp_sg9q",
            "dataTypeName": "number",
            "description": "This column was automatically created in order to record in what polygon from the dataset 'SF Find Neighborhoods' (6qbp-sg9q) the point in column 'location' is located.  This enables the creation of region maps (choropleths) in the visualization canvas and data lens.",
            "position": 36,
            "renderTypeName": "number",
            "tableColumnId": 591225229
        }
    ],
    "publishing_department": "Fire Department",
    "rows_updated_at": "2024-12-22T10:19:16Z",
    "item_noun": "permit",
    "usefulness": 2,
    "report_category": "Safety",
    "periodic": "yes",
    "district_level": true,
    "whom_it_may_interest": "Government safety regulators, property developers, fire safety researchers",
    "data_validated": true,
    "queries": {
        "Monthly": "SELECT date_trunc_ym(permit_application_date) AS month, COUNT(*) AS count, permit_type, battalion, supervisor_district WHERE permit_application_date >= '2022-09-01' GROUP BY month, permit_type, battalion, supervisor_district ORDER BY month, permit_type, battalion, supervisor_district",
        "Yearly": "SELECT date_trunc_y(permit_application_date) AS year, COUNT(*) AS count, permit_type, battalion, supervisor_district WHERE permit_application_date >= '2022-09-01' GROUP BY year, permit_type, battalion, supervisor_district ORDER BY month, permit_type, battalion, supervisor_district"
    }
}