{
    "category": "Transportation",
    "endpoint": "hi6h-neyh",
    "url": "https://data.sfgov.org/Transportation/Parking-regulations-except-non-metered-color-curb-/hi6h-neyh",
    "title": "Parking regulations (except non-metered color curb)",
    "description": "<strong>A. SUMMARY </strong>\nParking regulations by blockface for the City of San Francisco. Includes the following regulations: Residential Parking Permits, Time limits, Government Permit, No overnight, Oversized Vehicle. Does not include non metered color curb or curb cuts.\n\nUpdate as of 1/1/2018: started recording No parking any time (regulations like \"\"TOW AWAY NO PARKING\"\"), Limited No Parking (tow-away or no parking for certain periods of the day),\n\n<strong>B. METHODOLOGY</strong>\nMix of manual updates and data compilation.\n\n<strong>C. UPDATE FREQUENCY  </strong>\nUpdated as MTA Board resolutions are passed that impact parking regulations. \n\n<strong>D. OTHER CRITICAL INFO  </strong>\nThis dataset has not been comprehensively updated or vetted for accuracy. Dataset does not include color curb regulations such as loading zones or blue zones. Does not include detailed information for metered parking such as cap color or operating hours, which is contained in a separate relational database maintained by SFpark. No parking any time block faces were verified using Google Streetview, and only for Mission Bay blockfaces (Feburary 2017). \"",
    "columns": [
        {
            "name": "objectid",
            "fieldName": "objectid",
            "dataTypeName": "text",
            "description": "An ObjectID is a unique, not null integer field used to uniquely identify rows in tables in a ESRI geodatabase",
            "position": 1,
            "renderTypeName": "text",
            "tableColumnId": 588430524
        },
        {
            "name": "AGENCY",
            "fieldName": "agency",
            "dataTypeName": "text",
            "description": "The agency for which a Government Permit is allowed on that blockface",
            "position": 3,
            "renderTypeName": "text",
            "tableColumnId": 588430326
        },
        {
            "name": "REGULATION",
            "fieldName": "regulation",
            "dataTypeName": "text",
            "description": "Primary parking regulation applied to that blockface - Government permit, No overnight parking, RPP, Time limited, No parking any time, Unregulated. In the case of Residential Parking Permit areas, there is also a time limit for non-RPP holders, specified in the \"HrLimit\" field",
            "position": 4,
            "renderTypeName": "text",
            "tableColumnId": 588430327
        },
        {
            "name": "DAYS",
            "fieldName": "days",
            "dataTypeName": "text",
            "description": "Days for which regulation is in effect",
            "position": 5,
            "renderTypeName": "text",
            "tableColumnId": 588430328
        },
        {
            "name": "HOURS",
            "fieldName": "hours",
            "dataTypeName": "text",
            "description": "Hours for which regulation is in effect",
            "position": 6,
            "renderTypeName": "text",
            "tableColumnId": 588430329
        },
        {
            "name": "HRS_BEGIN",
            "fieldName": "hrs_begin",
            "dataTypeName": "text",
            "description": "",
            "position": 7,
            "renderTypeName": "text",
            "tableColumnId": 588430330
        },
        {
            "name": "HRS_END",
            "fieldName": "hrs_end",
            "dataTypeName": "text",
            "description": "",
            "position": 8,
            "renderTypeName": "text",
            "tableColumnId": 588430331
        },
        {
            "name": "REGDETAILS",
            "fieldName": "regdetails",
            "dataTypeName": "text",
            "description": "",
            "position": 9,
            "renderTypeName": "text",
            "tableColumnId": 588430332
        },
        {
            "name": "MODIFIED",
            "fieldName": "modified",
            "dataTypeName": "text",
            "description": "",
            "position": 10,
            "renderTypeName": "text",
            "tableColumnId": 588430333
        },
        {
            "name": "EDITOR",
            "fieldName": "editor",
            "dataTypeName": "text",
            "description": "",
            "position": 11,
            "renderTypeName": "text",
            "tableColumnId": 588430334
        },
        {
            "name": "RPPAREA1",
            "fieldName": "rpparea1",
            "dataTypeName": "text",
            "description": "",
            "position": 12,
            "renderTypeName": "text",
            "tableColumnId": 588430335
        },
        {
            "name": "RPPAREA2",
            "fieldName": "rpparea2",
            "dataTypeName": "text",
            "description": "",
            "position": 13,
            "renderTypeName": "text",
            "tableColumnId": 588430336
        },
        {
            "name": "RPPAREA3",
            "fieldName": "rpparea3",
            "dataTypeName": "text",
            "description": "",
            "position": 14,
            "renderTypeName": "text",
            "tableColumnId": 588430337
        },
        {
            "name": "FID_100",
            "fieldName": "fid_100",
            "dataTypeName": "text",
            "description": "",
            "position": 15,
            "renderTypeName": "text",
            "tableColumnId": 588430338
        },
        {
            "name": "LENGTH_FT",
            "fieldName": "length_ft",
            "dataTypeName": "text",
            "description": "",
            "position": 16,
            "renderTypeName": "text",
            "tableColumnId": 588430339
        },
        {
            "name": "CONFLICT",
            "fieldName": "conflict",
            "dataTypeName": "text",
            "description": "",
            "position": 17,
            "renderTypeName": "text",
            "tableColumnId": 588430340
        },
        {
            "name": "ENACTED",
            "fieldName": "enacted",
            "dataTypeName": "text",
            "description": "Month and year of MTA Board resolution passed",
            "position": 18,
            "renderTypeName": "text",
            "tableColumnId": 588430341
        },
        {
            "name": "CREATED_US",
            "fieldName": "created_us",
            "dataTypeName": "text",
            "description": "",
            "position": 19,
            "renderTypeName": "text",
            "tableColumnId": 588430342
        },
        {
            "name": "CREATED_DA",
            "fieldName": "created_da",
            "dataTypeName": "text",
            "description": "",
            "position": 20,
            "renderTypeName": "text",
            "tableColumnId": 588430343
        },
        {
            "name": "LAST_EDITE",
            "fieldName": "last_edite",
            "dataTypeName": "text",
            "description": "",
            "position": 21,
            "renderTypeName": "text",
            "tableColumnId": 588430344
        },
        {
            "name": "LAST_EDI_1",
            "fieldName": "last_edi_1",
            "dataTypeName": "text",
            "description": "",
            "position": 22,
            "renderTypeName": "text",
            "tableColumnId": 588430345
        },
        {
            "name": "HRLIMIT",
            "fieldName": "hrlimit",
            "dataTypeName": "text",
            "description": "Max number of hours allowed for parking on that blockface (unless RPP holder)",
            "position": 23,
            "renderTypeName": "text",
            "tableColumnId": 588430346
        },
        {
            "name": "CREATED_USER",
            "fieldName": "created_user",
            "dataTypeName": "text",
            "description": "",
            "position": 24,
            "renderTypeName": "text",
            "tableColumnId": 588430347
        },
        {
            "name": "CREATED_DATE",
            "fieldName": "created_date",
            "dataTypeName": "text",
            "description": "",
            "position": 25,
            "renderTypeName": "text",
            "tableColumnId": 588430348
        },
        {
            "name": "LAST_EDITED_USER",
            "fieldName": "last_edited_user",
            "dataTypeName": "text",
            "description": "",
            "position": 26,
            "renderTypeName": "text",
            "tableColumnId": 588430349
        },
        {
            "name": "LAST_EDITED_DATE",
            "fieldName": "last_edited_date",
            "dataTypeName": "text",
            "description": "",
            "position": 27,
            "renderTypeName": "text",
            "tableColumnId": 588430350
        },
        {
            "name": "RPP_SYM",
            "fieldName": "rpp_sym",
            "dataTypeName": "text",
            "description": "",
            "position": 28,
            "renderTypeName": "text",
            "tableColumnId": 588430351
        },
        {
            "name": "MTAB_DATE",
            "fieldName": "mtab_date",
            "dataTypeName": "text",
            "description": "",
            "position": 29,
            "renderTypeName": "text",
            "tableColumnId": 588430352
        },
        {
            "name": "MTAB_MOTION",
            "fieldName": "mtab_motion",
            "dataTypeName": "text",
            "description": "",
            "position": 30,
            "renderTypeName": "text",
            "tableColumnId": 588430353
        },
        {
            "name": "MTAB_RESO_TEXT",
            "fieldName": "mtab_reso_text",
            "dataTypeName": "text",
            "description": "",
            "position": 31,
            "renderTypeName": "text",
            "tableColumnId": 588430354
        },
        {
            "name": "SYM_RPP2",
            "fieldName": "sym_rpp2",
            "dataTypeName": "text",
            "description": "",
            "position": 32,
            "renderTypeName": "text",
            "tableColumnId": 588430355
        },
        {
            "name": "GLOBALID",
            "fieldName": "globalid",
            "dataTypeName": "text",
            "description": "",
            "position": 33,
            "renderTypeName": "text",
            "tableColumnId": 588430356
        },
        {
            "name": "EXCEPTIONS",
            "fieldName": "exceptions",
            "dataTypeName": "text",
            "description": "",
            "position": 34,
            "renderTypeName": "text",
            "tableColumnId": 588430357
        },
        {
            "name": "FROM_TIME",
            "fieldName": "from_time",
            "dataTypeName": "text",
            "description": "",
            "position": 35,
            "renderTypeName": "text",
            "tableColumnId": 588430358
        },
        {
            "name": "TO_TIME",
            "fieldName": "to_time",
            "dataTypeName": "text",
            "description": "",
            "position": 36,
            "renderTypeName": "text",
            "tableColumnId": 588430359
        },
        {
            "name": "shape",
            "fieldName": "shape",
            "dataTypeName": "multiline",
            "description": "",
            "position": 37,
            "renderTypeName": "multiline",
            "tableColumnId": 588430360
        },
        {
            "name": "data_as_of",
            "fieldName": "data_as_of",
            "dataTypeName": "calendar_date",
            "description": "Timestamp when the data was last processed",
            "position": 38,
            "renderTypeName": "calendar_date",
            "tableColumnId": 588430361
        },
        {
            "name": "analysis_neighborhood",
            "fieldName": "analysis_neighborhood",
            "dataTypeName": "text",
            "description": "Neighborhood associated with the midopint of the geographic feature",
            "position": 39,
            "renderTypeName": "text",
            "tableColumnId": 588430362
        },
        {
            "name": "supervisor_district",
            "fieldName": "supervisor_district",
            "dataTypeName": "text",
            "description": "Current supervisor district associated with the midopint of the geographic feature",
            "position": 40,
            "renderTypeName": "text",
            "tableColumnId": 588430363
        },
        {
            "name": "data_loaded_at",
            "fieldName": "data_loaded_at",
            "dataTypeName": "calendar_date",
            "description": "Timestamp when the data was loaded into the Open Data Portal",
            "position": 41,
            "renderTypeName": "calendar_date",
            "tableColumnId": 588430364
        }
    ],
    "publishing_department": "Municipal Transportation Agency ",
    "rows_updated_at": "2024-09-21T17:12:07Z",
    "item_noun": "Parking regulation",
    "usefulness": 1,
    "report_category": "Transportation",
    "NumericFields": [
        "item_count"
    ],
    "CategoryFields": [
        "AGENCY",
        "REGULATION",
        "DAYS"
    ],
    "DateFields": [
        "month"
    ],
    "periodic": true,
    "district_level": true,
    "whom_it_may_interest": "Transport policymakers, city planners, residents of San Francisco looking for parking information, and companies that offer parking services.",
    "data_validated": true,
    "queries": {
        "Monthly": "SELECT date_trunc_ym(data_as_of) AS month, COUNT(*) AS item_count, AGENCY, REGULATION, DAYS WHERE data_as_of >= start_date GROUP BY month, AGENCY, REGULATION, DAYS",
        "Yearly": "SELECT date_trunc_y(data_as_of) AS year, COUNT(*) AS item_count, AGENCY, REGULATION, DAYS WHERE data_as_of >= start_date GROUP BY year, AGENCY, REGULATION, DAYS"
    }
}