{
    "category": "Transportation",
    "endpoint": "nz48-2k5q",
    "url": "https://data.sfgov.org/Transportation/MTA-Fuel-Usage/nz48-2k5q",
    "title": "MTA Fuel Usage",
    "description": "The Municipal Transportation Agency (MTA) uses a variety of fuels for its vehicles. This data set provides information on fuel type and the number of gallons used by each MTA facility. Multiple lines of data for the same date indicates each instance of fueling at the specific facility. \n\nData is provided annually on a fiscal year basis.",
    "columns": [
        {
            "name": "Date",
            "fieldName": "date",
            "dataTypeName": "calendar_date",
            "description": "",
            "position": 1,
            "renderTypeName": "calendar_date",
            "tableColumnId": 452448555
        },
        {
            "name": "Place",
            "fieldName": "place",
            "dataTypeName": "text",
            "description": "",
            "position": 2,
            "renderTypeName": "text",
            "tableColumnId": 452448556
        },
        {
            "name": "Fuel Type",
            "fieldName": "fuel_type",
            "dataTypeName": "text",
            "description": "",
            "position": 3,
            "renderTypeName": "text",
            "tableColumnId": 452448558
        },
        {
            "name": "Gallons",
            "fieldName": "gallons",
            "dataTypeName": "number",
            "description": "",
            "position": 4,
            "renderTypeName": "number",
            "tableColumnId": 452448557
        }
    ],
    "publishing_department": "Municipal Transportation Agency ",
    "rows_updated_at": "2020-02-21T19:12:36Z"
}