{
    "category": "Housing and Buildings",
    "endpoint": "pa56-ek2h",
    "url": "https://data.sfgov.org/Housing-and-Buildings/Reference-Assessor-Recorder-Property-Class-Codes/pa56-ek2h",
    "title": "Reference: Assessor-Recorder Property Class Codes",
    "description": "Property class code reference dataset for the Assessor-Recorder historical secured property tax dataset. https://data.sfgov.org/d/wv5m-vpq2 Use codes are a superset of property class codes. Both codes include definitions.",
    "columns": [
        {
            "name": "Use Code",
            "fieldName": "use_code",
            "dataTypeName": "text",
            "description": "Use Codes group together related property class codes. They are defined by the field Use Definition. See also the field \"Property Class Code.\"",
            "position": 1,
            "renderTypeName": "text",
            "tableColumnId": 363479218
        },
        {
            "name": "Use Definition",
            "fieldName": "use_definition",
            "dataTypeName": "text",
            "description": "The definition for the field \"Use Code.\"",
            "position": 2,
            "renderTypeName": "text",
            "tableColumnId": 363479219
        },
        {
            "name": "Class Code",
            "fieldName": "class_code",
            "dataTypeName": "text",
            "description": "Property type code defined in the field \"Class Definition.\" \n\nPlease note, VCIX was truncated in the source and at the time records marked VCI could be VCIX. This is a rare code and indicates vacant land with restrictions as opposed to without.",
            "position": 3,
            "renderTypeName": "text",
            "tableColumnId": 363479220
        },
        {
            "name": "Class Definition",
            "fieldName": "class_definition",
            "dataTypeName": "text",
            "description": "Property type definition (name) based that defines the code in the field \"Class Code.\"\n\nPlease note, the property use code VCIX was truncated in the source and at the time records marked VCI could be VCIX. This is a rare code and indicates vacant land with restrictions as opposed to without.",
            "position": 4,
            "renderTypeName": "text",
            "tableColumnId": 363479221
        }
    ],
    "publishing_department": "Assessor-Recorder",
    "rows_updated_at": "2023-10-04T19:17:32Z"
}